MANIFEST.in
README.rst
setup.py
checkmate/__init__.py
checkmate/api_requester.py
checkmate/checkmate.py
checkmate/properties.py
checkmate/reservations.py
checkmate/version.py
checkmate_api.egg-info/PKG-INFO
checkmate_api.egg-info/SOURCES.txt
checkmate_api.egg-info/dependency_links.txt
checkmate_api.egg-info/requires.txt
checkmate_api.egg-info/top_level.txt