Metadata-Version: 1.0
Name: checkmate-api
Version: 1.0.0
Summary: A Python wrapper for the CheckMate REST API.
Home-page: http://www.checkmate.io/
Author: Ryan Eschinger
Author-email: ryanesc@gmail.com
License: UNKNOWN
Platform: UNKNOWN
